{
  "PenguPooh": {
    "original_username": "PenguPooh",
    "status": "exists",
    "profile_url": "https://x.com/PenguPooh",
    "checked_at": "2025-08-14T13:23:44.425370",
    "last_updated": "2025-08-14T13:23:44.425391"
  },
  "paoacflores": {
    "original_username": "paoacflores",
    "status": "exists",
    "profile_url": "https://x.com/paoacflores",
    "checked_at": "2025-08-14T13:23:45.711029",
    "last_updated": "2025-08-14T13:23:45.711038"
  },
  "_AiBiam": {
    "original_username": "_AiBiam",
    "status": "exists",
    "profile_url": "https://x.com/_AiBiam",
    "checked_at": "2025-08-14T13:23:45.967701",
    "last_updated": "2025-08-14T13:23:45.967710"
  },
  "sukaihan": {
    "original_username": "sukaihan",
    "status": "exists",
    "profile_url": "https://x.com/sukaihan",
    "checked_at": "2025-08-14T13:23:55.881245",
    "last_updated": "2025-08-14T13:23:55.881279"
  },
  "nemuiryuu": {
    "original_username": "nemuiryuu",
    "status": "exists",
    "profile_url": "https://x.com/nemuiryuu",
    "checked_at": "2025-08-14T13:23:57.064202",
    "last_updated": "2025-08-14T13:23:57.064213"
  },
  "TheFredaLee": {
    "original_username": "TheFredaLee",
    "status": "exists",
    "profile_url": "https://x.com/TheFredaLee",
    "checked_at": "2025-08-14T13:23:57.800604",
    "last_updated": "2025-08-14T13:23:57.800613"
  },
  "Nettaaaaaaaa": {
    "original_username": "Nettaaaaaaaa",
    "status": "exists",
    "profile_url": "https://x.com/Nettaaaaaaaa",
    "checked_at": "2025-08-14T13:24:06.374720",
    "last_updated": "2025-08-14T13:24:06.374740"
  },
  "t00_Far": {
    "original_username": "t00_Far",
    "status": "exists",
    "profile_url": "https://x.com/t00_Far",
    "checked_at": "2025-08-14T13:24:09.000668",
    "last_updated": "2025-08-14T13:24:09.000690"
  },
  "kid_slasher": {
    "original_username": "kid_slasher",
    "status": "exists",
    "profile_url": "https://x.com/kid_slasher",
    "checked_at": "2025-08-14T13:24:10.000822",
    "last_updated": "2025-08-14T13:24:10.000831"
  },
  "BarackOMamba": {
    "original_username": "BarackOMamba",
    "status": "exists",
    "profile_url": "https://x.com/BarackOMamba",
    "checked_at": "2025-08-14T13:24:18.361648",
    "last_updated": "2025-08-14T13:24:18.361671"
  },
  "gtjio": {
    "original_username": "gtjio",
    "status": "exists",
    "profile_url": "https://x.com/gtjio",
    "checked_at": "2025-08-14T13:24:20.501151",
    "last_updated": "2025-08-14T13:24:20.501164"
  },
  "brokenwing2005": {
    "original_username": "brokenwing2005",
    "status": "exists",
    "profile_url": "https://x.com/brokenwing2005",
    "checked_at": "2025-08-14T13:24:20.761831",
    "last_updated": "2025-08-14T13:24:20.761837"
  },
  "Keltounet": {
    "original_username": "Keltounet",
    "status": "exists",
    "profile_url": "https://x.com/Keltounet",
    "checked_at": "2025-08-14T13:24:29.341236",
    "last_updated": "2025-08-14T13:24:29.341245"
  },
  "digimishkas": {
    "original_username": "digimishkas",
    "status": "exists",
    "profile_url": "https://x.com/digimishkas",
    "checked_at": "2025-08-14T13:24:31.899371",
    "last_updated": "2025-08-14T13:24:31.899381"
  },
  "amandagabr1elle": {
    "original_username": "amandagabr1elle",
    "status": "exists",
    "profile_url": "https://x.com/amandagabr1elle",
    "checked_at": "2025-08-14T13:24:32.950940",
    "last_updated": "2025-08-14T13:24:32.950953"
  },
  "leredza": {
    "original_username": "leredza",
    "status": "exists",
    "profile_url": "https://x.com/leredza",
    "checked_at": "2025-08-14T13:24:40.139088",
    "last_updated": "2025-08-14T13:24:40.139147"
  },
  "Strangeland_Elf": {
    "original_username": "Strangeland_Elf",
    "status": "exists",
    "profile_url": "https://x.com/Strangeland_Elf",
    "checked_at": "2025-08-14T13:24:43.856154",
    "last_updated": "2025-08-14T13:24:43.856205"
  },
  "sluttyseagull": {
    "original_username": "sluttyseagull",
    "status": "exists",
    "profile_url": "https://x.com/sluttyseagull",
    "checked_at": "2025-08-14T13:24:44.547493",
    "last_updated": "2025-08-14T13:24:44.547511"
  },
  "jki82": {
    "original_username": "jki82",
    "status": "exists",
    "profile_url": "https://x.com/jki82",
    "checked_at": "2025-08-14T13:24:50.662734",
    "last_updated": "2025-08-14T13:24:50.662756"
  },
  "leenie909": {
    "original_username": "leenie909",
    "status": "exists",
    "profile_url": "https://x.com/leenie909",
    "checked_at": "2025-08-14T13:24:55.281476",
    "last_updated": "2025-08-14T13:24:55.281525"
  },
  "mircifer": {
    "original_username": "mircifer",
    "status": "exists",
    "profile_url": "https://x.com/mircifer",
    "checked_at": "2025-08-14T13:24:55.722564",
    "last_updated": "2025-08-14T13:24:55.722578"
  },
  "__Sadi__": {
    "original_username": "__Sadi__",
    "status": "exists",
    "profile_url": "https://x.com/__Sadi__",
    "checked_at": "2025-08-14T13:25:02.656046",
    "last_updated": "2025-08-14T13:25:02.656096"
  },
  "ZephyrRz": {
    "original_username": "ZephyrRz",
    "status": "exists",
    "profile_url": "https://x.com/ZephyrRz",
    "checked_at": "2025-08-14T13:25:06.233424",
    "last_updated": "2025-08-14T13:25:06.233460"
  },
  "ItsCee_xo": {
    "original_username": "ItsCee_xo",
    "status": "exists",
    "profile_url": "https://x.com/ItsCee_xo",
    "checked_at": "2025-08-14T13:25:07.568272",
    "last_updated": "2025-08-14T13:25:07.568280"
  },
  "Osephala": {
    "original_username": "Osephala",
    "status": "exists",
    "profile_url": "https://x.com/Osephala",
    "checked_at": "2025-08-14T13:25:14.397936",
    "last_updated": "2025-08-14T13:25:14.397945"
  },
  "Daina_91880": {
    "original_username": "Daina_91880",
    "status": "exists",
    "profile_url": "https://x.com/Daina_91880",
    "checked_at": "2025-08-14T13:25:17.455699",
    "last_updated": "2025-08-14T13:25:17.455710"
  },
  "jinetflix": {
    "original_username": "jinetflix",
    "status": "exists",
    "profile_url": "https://x.com/jinetflix",
    "checked_at": "2025-08-14T13:25:19.772168",
    "last_updated": "2025-08-14T13:25:19.772179"
  },
  "AngieElliott30": {
    "original_username": "AngieElliott30",
    "status": "exists",
    "profile_url": "https://x.com/AngieElliott30",
    "checked_at": "2025-08-14T13:25:25.653687",
    "last_updated": "2025-08-14T13:25:25.653734"
  },
  "tearvnclw": {
    "original_username": "tearvnclw",
    "status": "exists",
    "profile_url": "https://x.com/tearvnclw",
    "checked_at": "2025-08-14T13:25:29.363978",
    "last_updated": "2025-08-14T13:25:29.363987"
  },
  "rahbeeuh": {
    "original_username": "rahbeeuh",
    "status": "exists",
    "profile_url": "https://x.com/rahbeeuh",
    "checked_at": "2025-08-14T13:25:31.075851",
    "last_updated": "2025-08-14T13:25:31.075871"
  },
  "sorryjzargo": {
    "original_username": "sorryjzargo",
    "status": "exists",
    "profile_url": "https://x.com/sorryjzargo",
    "checked_at": "2025-08-14T13:25:35.928012",
    "last_updated": "2025-08-14T13:25:35.928019"
  },
  "Garrsett": {
    "original_username": "Garrsett",
    "status": "exists",
    "profile_url": "https://x.com/Garrsett",
    "checked_at": "2025-08-14T13:25:40.733703",
    "last_updated": "2025-08-14T13:25:40.733727"
  },
  "nilesdennard": {
    "original_username": "nilesdennard",
    "status": "exists",
    "profile_url": "https://x.com/nilesdennard",
    "checked_at": "2025-08-14T13:25:42.797330",
    "last_updated": "2025-08-14T13:25:42.797341"
  },
  "TheNewYorkDoll": {
    "original_username": "TheNewYorkDoll",
    "status": "exists",
    "profile_url": "https://x.com/TheNewYorkDoll",
    "checked_at": "2025-08-14T13:25:46.377415",
    "last_updated": "2025-08-14T13:25:46.377439"
  },
  "neverlandvicki": {
    "original_username": "neverlandvicki",
    "status": "exists",
    "profile_url": "https://x.com/neverlandvicki",
    "checked_at": "2025-08-14T13:25:51.145959",
    "last_updated": "2025-08-14T13:25:51.145967"
  },
  "oh__honey__": {
    "original_username": "oh__honey__",
    "status": "exists",
    "profile_url": "https://x.com/oh__honey__",
    "checked_at": "2025-08-14T13:25:52.941170",
    "last_updated": "2025-08-14T13:25:52.941177"
  },
  "iamAlyloony": {
    "original_username": "iamAlyloony",
    "status": "exists",
    "profile_url": "https://x.com/iamAlyloony",
    "checked_at": "2025-08-14T13:25:56.747556",
    "last_updated": "2025-08-14T13:25:56.747574"
  },
  "midoritakamine": {
    "original_username": "midoritakamine",
    "status": "exists",
    "profile_url": "https://x.com/midoritakamine",
    "checked_at": "2025-08-14T13:26:02.079044",
    "last_updated": "2025-08-14T13:26:02.079068"
  },
  "raoufarif": {
    "original_username": "raoufarif",
    "status": "exists",
    "profile_url": "https://x.com/raoufarif",
    "checked_at": "2025-08-14T13:26:03.976046",
    "last_updated": "2025-08-14T13:26:03.976057"
  },
  "chris4nature": {
    "original_username": "chris4nature",
    "status": "exists",
    "profile_url": "https://x.com/chris4nature",
    "checked_at": "2025-08-14T13:26:07.544333",
    "last_updated": "2025-08-14T13:26:07.544379"
  },
  "pab0sarang": {
    "original_username": "pab0sarang",
    "status": "exists",
    "profile_url": "https://x.com/pab0sarang",
    "checked_at": "2025-08-14T13:26:13.927209",
    "last_updated": "2025-08-14T13:26:13.927256"
  },
  "Didi_AW_": {
    "original_username": "Didi_AW_",
    "status": "exists",
    "profile_url": "https://x.com/Didi_AW_",
    "checked_at": "2025-08-14T13:26:14.419530",
    "last_updated": "2025-08-14T13:26:14.419542"
  },
  "johnmyersart": {
    "original_username": "johnmyersart",
    "status": "exists",
    "profile_url": "https://x.com/johnmyersart",
    "checked_at": "2025-08-14T13:26:17.914431",
    "last_updated": "2025-08-14T13:26:17.914445"
  },
  "sushi4ever_": {
    "original_username": "sushi4ever_",
    "status": "exists",
    "profile_url": "https://x.com/sushi4ever_",
    "checked_at": "2025-08-14T13:26:24.346154",
    "last_updated": "2025-08-14T13:26:24.346176"
  },
  "racunberapi": {
    "original_username": "racunberapi",
    "status": "exists",
    "profile_url": "https://x.com/racunberapi",
    "checked_at": "2025-08-14T13:26:25.602972",
    "last_updated": "2025-08-14T13:26:25.602982"
  },
  "kudiak": {
    "original_username": "kudiak",
    "status": "exists",
    "profile_url": "https://x.com/kudiak",
    "checked_at": "2025-08-14T13:26:28.219262",
    "last_updated": "2025-08-14T13:26:28.219271"
  },
  "ladyriven": {
    "original_username": "ladyriven",
    "status": "exists",
    "profile_url": "https://x.com/ladyriven",
    "checked_at": "2025-08-14T13:26:35.695015",
    "last_updated": "2025-08-14T13:26:35.695062"
  },
  "ajhmac98": {
    "original_username": "ajhmac98",
    "status": "exists",
    "profile_url": "https://x.com/ajhmac98",
    "checked_at": "2025-08-14T13:26:37.814295",
    "last_updated": "2025-08-14T13:26:37.814304"
  },
  "sususuyos": {
    "original_username": "sususuyos",
    "status": "exists",
    "profile_url": "https://x.com/sususuyos",
    "checked_at": "2025-08-14T13:26:40.235291",
    "last_updated": "2025-08-14T13:26:40.235308"
  },
  "cha_dhira": {
    "original_username": "cha_dhira",
    "status": "exists",
    "profile_url": "https://x.com/cha_dhira",
    "checked_at": "2025-08-14T13:26:46.916264",
    "last_updated": "2025-08-14T13:26:46.916291"
  },
  "ritaresarian": {
    "original_username": "ritaresarian",
    "status": "exists",
    "profile_url": "https://x.com/ritaresarian",
    "checked_at": "2025-08-14T13:26:49.722591",
    "last_updated": "2025-08-14T13:26:49.722646"
  },
  "thetidebreaks": {
    "original_username": "thetidebreaks",
    "status": "exists",
    "profile_url": "https://x.com/thetidebreaks",
    "checked_at": "2025-08-14T13:26:51.801319",
    "last_updated": "2025-08-14T13:26:51.801325"
  },
  "TheRaikume": {
    "original_username": "TheRaikume",
    "status": "exists",
    "profile_url": "https://x.com/TheRaikume",
    "checked_at": "2025-08-14T13:26:57.162620",
    "last_updated": "2025-08-14T13:26:57.162634"
  },
  "AKindOfRainyDay": {
    "original_username": "AKindOfRainyDay",
    "status": "exists",
    "profile_url": "https://x.com/AKindOfRainyDay",
    "checked_at": "2025-08-14T13:27:01.055134",
    "last_updated": "2025-08-14T13:27:01.055211"
  },
  "MuchCwtchly": {
    "original_username": "MuchCwtchly",
    "status": "exists",
    "profile_url": "https://x.com/MuchCwtchly",
    "checked_at": "2025-08-14T13:27:02.290021",
    "last_updated": "2025-08-14T13:27:02.290031"
  },
  "Scorpioest": {
    "original_username": "Scorpioest",
    "status": "exists",
    "profile_url": "https://x.com/Scorpioest",
    "checked_at": "2025-08-14T13:27:07.700596",
    "last_updated": "2025-08-14T13:27:07.700613"
  },
  "RubbinTummy": {
    "original_username": "RubbinTummy",
    "status": "exists",
    "profile_url": "https://x.com/RubbinTummy",
    "checked_at": "2025-08-14T13:27:11.940372",
    "last_updated": "2025-08-14T13:27:11.940391"
  },
  "rjtremor": {
    "original_username": "rjtremor",
    "status": "exists",
    "profile_url": "https://x.com/rjtremor",
    "checked_at": "2025-08-14T13:27:13.887206",
    "last_updated": "2025-08-14T13:27:13.887218"
  },
  "RmrcMY": {
    "original_username": "RmrcMY",
    "status": "exists",
    "profile_url": "https://x.com/RmrcMY",
    "checked_at": "2025-08-14T13:27:19.506658",
    "last_updated": "2025-08-14T13:27:19.506670"
  },
  "mikkipedia": {
    "original_username": "mikkipedia",
    "status": "exists",
    "profile_url": "https://x.com/mikkipedia",
    "checked_at": "2025-08-14T13:27:23.232124",
    "last_updated": "2025-08-14T13:27:23.232133"
  },
  "tisheriffic": {
    "original_username": "tisheriffic",
    "status": "exists",
    "profile_url": "https://x.com/tisheriffic",
    "checked_at": "2025-08-14T13:27:25.042799",
    "last_updated": "2025-08-14T13:27:25.042809"
  },
  "miamifasol": {
    "original_username": "miamifasol",
    "status": "exists",
    "profile_url": "https://x.com/miamifasol",
    "checked_at": "2025-08-14T13:27:31.045462",
    "last_updated": "2025-08-14T13:27:31.045488"
  },
  "cirrysx": {
    "original_username": "cirrysx",
    "status": "exists",
    "profile_url": "https://x.com/cirrysx",
    "checked_at": "2025-08-14T13:27:34.087536",
    "last_updated": "2025-08-14T13:27:34.087598"
  },
  "sasha_feather": {
    "original_username": "sasha_feather",
    "status": "exists",
    "profile_url": "https://x.com/sasha_feather",
    "checked_at": "2025-08-14T13:27:36.536768",
    "last_updated": "2025-08-14T13:27:36.536776"
  },
  "KristofurFox": {
    "original_username": "KristofurFox",
    "status": "exists",
    "profile_url": "https://x.com/KristofurFox",
    "checked_at": "2025-08-14T13:27:41.631924",
    "last_updated": "2025-08-14T13:27:41.631975"
  },
  "odetovalerie": {
    "original_username": "odetovalerie",
    "status": "exists",
    "profile_url": "https://x.com/odetovalerie",
    "checked_at": "2025-08-14T13:27:44.762534",
    "last_updated": "2025-08-14T13:27:44.762591"
  },
  "ErynithMawen": {
    "original_username": "ErynithMawen",
    "status": "exists",
    "profile_url": "https://x.com/ErynithMawen",
    "checked_at": "2025-08-14T13:27:47.098896",
    "last_updated": "2025-08-14T13:27:47.098905"
  },
  "B_Keps": {
    "original_username": "B_Keps",
    "status": "exists",
    "profile_url": "https://x.com/B_Keps",
    "checked_at": "2025-08-14T13:27:52.652113",
    "last_updated": "2025-08-14T13:27:52.652163"
  },
  "wearpy": {
    "original_username": "wearpy",
    "status": "exists",
    "profile_url": "https://x.com/wearpy",
    "checked_at": "2025-08-14T13:27:56.252186",
    "last_updated": "2025-08-14T13:27:56.252215"
  },
  "donghaeyah": {
    "original_username": "donghaeyah",
    "status": "exists",
    "profile_url": "https://x.com/donghaeyah",
    "checked_at": "2025-08-14T13:27:58.776507",
    "last_updated": "2025-08-14T13:27:58.776521"
  },
  "jerees": {
    "original_username": "jerees",
    "status": "exists",
    "profile_url": "https://x.com/jerees",
    "checked_at": "2025-08-14T13:28:04.476194",
    "last_updated": "2025-08-14T13:28:04.476207"
  },
  "pandabatai": {
    "original_username": "pandabatai",
    "status": "exists",
    "profile_url": "https://x.com/pandabatai",
    "checked_at": "2025-08-14T13:28:07.292582",
    "last_updated": "2025-08-14T13:28:07.292597"
  },
  "zaynsbravery": {
    "original_username": "zaynsbravery",
    "status": "exists",
    "profile_url": "https://x.com/zaynsbravery",
    "checked_at": "2025-08-14T13:28:10.704993",
    "last_updated": "2025-08-14T13:28:10.705002"
  },
  "nrokiki": {
    "original_username": "nrokiki",
    "status": "exists",
    "profile_url": "https://x.com/nrokiki",
    "checked_at": "2025-08-14T13:28:15.788116",
    "last_updated": "2025-08-14T13:28:15.788153"
  },
  "poetrynmadness": {
    "original_username": "poetrynmadness",
    "status": "exists",
    "profile_url": "https://x.com/poetrynmadness",
    "checked_at": "2025-08-14T13:28:18.499786",
    "last_updated": "2025-08-14T13:28:18.499800"
  },
  "flyinvisible": {
    "original_username": "flyinvisible",
    "status": "exists",
    "profile_url": "https://x.com/flyinvisible",
    "checked_at": "2025-08-14T13:28:21.698771",
    "last_updated": "2025-08-14T13:28:21.698809"
  },
  "cuteteakitty": {
    "original_username": "cuteteakitty",
    "status": "exists",
    "profile_url": "https://x.com/cuteteakitty",
    "checked_at": "2025-08-14T13:28:26.925781",
    "last_updated": "2025-08-14T13:28:26.925801"
  },
  "pantieschan": {
    "original_username": "pantieschan",
    "status": "exists",
    "profile_url": "https://x.com/pantieschan",
    "checked_at": "2025-08-14T13:28:29.651463",
    "last_updated": "2025-08-14T13:28:29.651472"
  },
  "dokyeem": {
    "original_username": "dokyeem",
    "status": "exists",
    "profile_url": "https://x.com/dokyeem",
    "checked_at": "2025-08-14T13:28:33.111946",
    "last_updated": "2025-08-14T13:28:33.111968"
  },
  "HuskyBro_Inc": {
    "original_username": "HuskyBro_Inc",
    "status": "exists",
    "profile_url": "https://x.com/HuskyBro_Inc",
    "checked_at": "2025-08-14T13:28:38.249454",
    "last_updated": "2025-08-14T13:28:38.249466"
  },
  "Foxtrot44": {
    "original_username": "Foxtrot44",
    "status": "exists",
    "profile_url": "https://x.com/Foxtrot44",
    "checked_at": "2025-08-14T13:28:41.756053",
    "last_updated": "2025-08-14T13:28:41.756067"
  },
  "Kittywink": {
    "original_username": "Kittywink",
    "status": "exists",
    "profile_url": "https://x.com/Kittywink",
    "checked_at": "2025-08-14T13:28:44.939323",
    "last_updated": "2025-08-14T13:28:44.939334"
  },
  "Other_Girl": {
    "original_username": "Other_Girl",
    "status": "exists",
    "profile_url": "https://x.com/Other_Girl",
    "checked_at": "2025-08-14T13:28:50.294110",
    "last_updated": "2025-08-14T13:28:50.294134"
  },
  "xsunsetbeauty": {
    "original_username": "xsunsetbeauty",
    "status": "exists",
    "profile_url": "https://x.com/xsunsetbeauty",
    "checked_at": "2025-08-14T13:28:52.774490",
    "last_updated": "2025-08-14T13:28:52.774499"
  },
  "soRobynNico": {
    "original_username": "soRobynNico",
    "status": "exists",
    "profile_url": "https://x.com/soRobynNico",
    "checked_at": "2025-08-14T13:28:56.329511",
    "last_updated": "2025-08-14T13:28:56.329534"
  },
  "LunaLovebomb": {
    "original_username": "LunaLovebomb",
    "status": "exists",
    "profile_url": "https://x.com/LunaLovebomb",
    "checked_at": "2025-08-14T13:29:00.516657",
    "last_updated": "2025-08-14T13:29:00.516681"
  },
  "LiberalsAreCool": {
    "original_username": "LiberalsAreCool",
    "status": "exists",
    "profile_url": "https://x.com/LiberalsAreCool",
    "checked_at": "2025-08-14T13:29:04.459670",
    "last_updated": "2025-08-14T13:29:04.459685"
  },
  "DurgeshG7": {
    "original_username": "DurgeshG7",
    "status": "exists",
    "profile_url": "https://x.com/DurgeshG7",
    "checked_at": "2025-08-14T13:29:07.788098",
    "last_updated": "2025-08-14T13:29:07.788112"
  },
  "Jannine_twt": {
    "original_username": "Jannine_twt",
    "status": "exists",
    "profile_url": "https://x.com/Jannine_twt",
    "checked_at": "2025-08-14T13:29:11.003091",
    "last_updated": "2025-08-14T13:29:11.003112"
  },
  "gonewiththeword": {
    "original_username": "gonewiththeword",
    "status": "exists",
    "profile_url": "https://x.com/gonewiththeword",
    "checked_at": "2025-08-14T13:29:15.666534",
    "last_updated": "2025-08-14T13:29:15.666555"
  },
  "janebracher": {
    "original_username": "janebracher",
    "status": "exists",
    "profile_url": "https://x.com/janebracher",
    "checked_at": "2025-08-14T13:29:18.501255",
    "last_updated": "2025-08-14T13:29:18.501263"
  },
  "h_quant": {
    "original_username": "h_quant",
    "status": "exists",
    "profile_url": "https://x.com/h_quant",
    "checked_at": "2025-08-14T13:29:23.064318",
    "last_updated": "2025-08-14T13:29:23.064335"
  },
  "lbreton": {
    "original_username": "lbreton",
    "status": "exists",
    "profile_url": "https://x.com/lbreton",
    "checked_at": "2025-08-14T13:29:26.788466",
    "last_updated": "2025-08-14T13:29:26.788489"
  },
  "SechanKV": {
    "original_username": "SechanKV",
    "status": "exists",
    "profile_url": "https://x.com/SechanKV",
    "checked_at": "2025-08-14T13:29:29.399212",
    "last_updated": "2025-08-14T13:29:29.399225"
  },
  "SatoshicKaleida": {
    "original_username": "SatoshicKaleida",
    "status": "exists",
    "profile_url": "https://x.com/SatoshicKaleida",
    "checked_at": "2025-08-14T13:29:33.665456",
    "last_updated": "2025-08-14T13:29:33.665501"
  },
  "NosajRellim": {
    "original_username": "NosajRellim",
    "status": "exists",
    "profile_url": "https://x.com/NosajRellim",
    "checked_at": "2025-08-14T13:29:39.165549",
    "last_updated": "2025-08-14T13:29:39.165580"
  },
  "Safe_Haven0419": {
    "original_username": "Safe_Haven0419",
    "status": "exists",
    "profile_url": "https://x.com/Safe_Haven0419",
    "checked_at": "2025-08-14T13:29:40.772327",
    "last_updated": "2025-08-14T13:29:40.772337"
  },
  "Eltalite": {
    "original_username": "Eltalite",
    "status": "exists",
    "profile_url": "https://x.com/Eltalite",
    "checked_at": "2025-08-14T13:29:45.408326",
    "last_updated": "2025-08-14T13:29:45.408363"
  },
  "earthumbrella": {
    "original_username": "earthumbrella",
    "status": "exists",
    "profile_url": "https://x.com/earthumbrella",
    "checked_at": "2025-08-14T13:29:49.660339",
    "last_updated": "2025-08-14T13:29:49.660384"
  },
  "burnbrights": {
    "original_username": "burnbrights",
    "status": "exists",
    "profile_url": "https://x.com/burnbrights",
    "checked_at": "2025-08-21T13:37:44.086083",
    "last_updated": "2025-08-21T13:37:44.086133"
  },
  "biblio_phile": {
    "original_username": "biblio_phile",
    "status": "exists",
    "profile_url": "https://x.com/biblio_phile",
    "checked_at": "2025-08-21T13:37:44.411253",
    "last_updated": "2025-08-21T13:37:44.411259"
  },
  "yanneekbrinson_": {
    "original_username": "yanneekbrinson_",
    "status": "exists",
    "profile_url": "https://x.com/yanneekbrinson_",
    "checked_at": "2025-08-21T13:37:44.539868",
    "last_updated": "2025-08-21T13:37:44.539878"
  },
  "onejiggynigga": {
    "original_username": "onejiggynigga",
    "status": "exists",
    "profile_url": "https://x.com/onejiggynigga",
    "checked_at": "2025-08-21T13:37:55.140307",
    "last_updated": "2025-08-21T13:37:55.140341"
  },
  "Jus_de_fruit": {
    "original_username": "Jus_de_fruit",
    "status": "exists",
    "profile_url": "https://x.com/Jus_de_fruit",
    "checked_at": "2025-08-21T13:37:55.442186",
    "last_updated": "2025-08-21T13:37:55.442196"
  },
  "kirstnicolexo": {
    "original_username": "kirstnicolexo",
    "status": "exists",
    "profile_url": "https://x.com/kirstnicolexo",
    "checked_at": "2025-08-21T13:37:55.535881",
    "last_updated": "2025-08-21T13:37:55.535891"
  },
  "LucknawiRooh": {
    "original_username": "LucknawiRooh",
    "status": "exists",
    "profile_url": "https://x.com/LucknawiRooh",
    "checked_at": "2025-08-21T13:38:06.257967",
    "last_updated": "2025-08-21T13:38:06.257992"
  },
  "HugsfromSA": {
    "original_username": "HugsfromSA",
    "status": "exists",
    "profile_url": "https://x.com/HugsfromSA",
    "checked_at": "2025-08-21T13:38:06.847527",
    "last_updated": "2025-08-21T13:38:06.847543"
  },
  "v23474": {
    "original_username": "v23474",
    "status": "exists",
    "profile_url": "https://x.com/v23474",
    "checked_at": "2025-08-21T13:38:07.333175",
    "last_updated": "2025-08-21T13:38:07.333188"
  },
  "sepuuut": {
    "original_username": "sepuuut",
    "status": "exists",
    "profile_url": "https://x.com/sepuuut",
    "checked_at": "2025-08-21T13:38:17.353467",
    "last_updated": "2025-08-21T13:38:17.353488"
  },
  "undyingodinsons": {
    "original_username": "undyingodinsons",
    "status": "exists",
    "profile_url": "https://x.com/undyingodinsons",
    "checked_at": "2025-08-21T13:38:17.495341",
    "last_updated": "2025-08-21T13:38:17.495350"
  },
  "foreverunfelled": {
    "original_username": "foreverunfelled",
    "status": "exists",
    "profile_url": "https://x.com/foreverunfelled",
    "checked_at": "2025-08-21T13:38:18.627644",
    "last_updated": "2025-08-21T13:38:18.627654"
  },
  "DrewWinchester": {
    "original_username": "DrewWinchester",
    "status": "exists",
    "profile_url": "https://x.com/DrewWinchester",
    "checked_at": "2025-08-21T13:38:28.319919",
    "last_updated": "2025-08-21T13:38:28.319964"
  },
  "ScorpTaurCapSag": {
    "original_username": "ScorpTaurCapSag",
    "status": "exists",
    "profile_url": "https://x.com/ScorpTaurCapSag",
    "checked_at": "2025-08-21T13:38:28.888474",
    "last_updated": "2025-08-21T13:38:28.888496"
  },
  "amynluv": {
    "original_username": "amynluv",
    "status": "exists",
    "profile_url": "https://x.com/amynluv",
    "checked_at": "2025-08-21T13:38:29.450161",
    "last_updated": "2025-08-21T13:38:29.450172"
  },
  "miyazawa_lulu": {
    "original_username": "miyazawa_lulu",
    "status": "exists",
    "profile_url": "https://x.com/miyazawa_lulu",
    "checked_at": "2025-08-21T13:38:39.481710",
    "last_updated": "2025-08-21T13:38:39.481756"
  },
  "DIY28": {
    "original_username": "DIY28",
    "status": "exists",
    "profile_url": "https://x.com/DIY28",
    "checked_at": "2025-08-21T13:38:39.797518",
    "last_updated": "2025-08-21T13:38:39.797526"
  },
  "VanessaRNMH": {
    "original_username": "VanessaRNMH",
    "status": "exists",
    "profile_url": "https://x.com/VanessaRNMH",
    "checked_at": "2025-08-21T13:38:39.970558",
    "last_updated": "2025-08-21T13:38:39.970567"
  },
  "shsalmahh29": {
    "original_username": "shsalmahh29",
    "status": "exists",
    "profile_url": "https://x.com/shsalmahh29",
    "checked_at": "2025-08-21T13:38:50.937890",
    "last_updated": "2025-08-21T13:38:50.937922"
  },
  "RekkaAlexiel": {
    "original_username": "RekkaAlexiel",
    "status": "exists",
    "profile_url": "https://x.com/RekkaAlexiel",
    "checked_at": "2025-08-21T13:38:51.580349",
    "last_updated": "2025-08-21T13:38:51.580368"
  },
  "berlee60": {
    "original_username": "berlee60",
    "status": "exists",
    "profile_url": "https://x.com/berlee60",
    "checked_at": "2025-08-21T13:38:51.626693",
    "last_updated": "2025-08-21T13:38:51.626705"
  },
  "inkdin": {
    "original_username": "inkdin",
    "status": "exists",
    "profile_url": "https://x.com/inkdin",
    "checked_at": "2025-08-21T13:39:01.787954",
    "last_updated": "2025-08-21T13:39:01.787995"
  },
  "aliceyinyang": {
    "original_username": "aliceyinyang",
    "status": "exists",
    "profile_url": "https://x.com/aliceyinyang",
    "checked_at": "2025-08-21T13:39:02.526550",
    "last_updated": "2025-08-21T13:39:02.526564"
  },
  "wincheswift": {
    "original_username": "wincheswift",
    "status": "exists",
    "profile_url": "https://x.com/wincheswift",
    "checked_at": "2025-08-21T13:39:03.330806",
    "last_updated": "2025-08-21T13:39:03.330814"
  },
  "I_NoiceLati": {
    "original_username": "I_NoiceLati",
    "status": "exists",
    "profile_url": "https://x.com/I_NoiceLati",
    "checked_at": "2025-08-21T13:39:12.944979",
    "last_updated": "2025-08-21T13:39:12.945011"
  },
  "__forceofnature": {
    "original_username": "__forceofnature",
    "status": "exists",
    "profile_url": "https://x.com/__forceofnature",
    "checked_at": "2025-08-21T13:39:14.814690",
    "last_updated": "2025-08-21T13:39:14.814700"
  },
  "louis0nfire": {
    "original_username": "louis0nfire",
    "status": "exists",
    "profile_url": "https://x.com/louis0nfire",
    "checked_at": "2025-08-21T13:39:15.433572",
    "last_updated": "2025-08-21T13:39:15.433592"
  },
  "owlyrapunzel": {
    "original_username": "owlyrapunzel",
    "status": "exists",
    "profile_url": "https://x.com/owlyrapunzel",
    "checked_at": "2025-08-21T13:39:24.104990",
    "last_updated": "2025-08-21T13:39:24.105008"
  },
  "makeshiftjen": {
    "original_username": "makeshiftjen",
    "status": "exists",
    "profile_url": "https://x.com/makeshiftjen",
    "checked_at": "2025-08-21T13:39:25.248630",
    "last_updated": "2025-08-21T13:39:25.248638"
  },
  "GuacaMochni": {
    "original_username": "GuacaMochni",
    "status": "exists",
    "profile_url": "https://x.com/GuacaMochni",
    "checked_at": "2025-08-21T13:39:26.157066",
    "last_updated": "2025-08-21T13:39:26.157075"
  },
  "TheWordN3rd": {
    "original_username": "TheWordN3rd",
    "status": "exists",
    "profile_url": "https://x.com/TheWordN3rd",
    "checked_at": "2025-08-21T13:39:34.332269",
    "last_updated": "2025-08-21T13:39:34.332301"
  },
  "TRICIA_FIIERCE": {
    "original_username": "TRICIA_FIIERCE",
    "status": "exists",
    "profile_url": "https://x.com/TRICIA_FIIERCE",
    "checked_at": "2025-08-21T13:39:37.132057",
    "last_updated": "2025-08-21T13:39:37.132076"
  },
  "theBook0fEli_": {
    "original_username": "theBook0fEli_",
    "status": "exists",
    "profile_url": "https://x.com/theBook0fEli_",
    "checked_at": "2025-08-21T13:39:37.204627",
    "last_updated": "2025-08-21T13:39:37.204638"
  },
  "tempusfrangit": {
    "original_username": "tempusfrangit",
    "status": "exists",
    "profile_url": "https://x.com/tempusfrangit",
    "checked_at": "2025-08-21T13:39:44.886705",
    "last_updated": "2025-08-21T13:39:44.886823"
  },
  "anotherschwab": {
    "original_username": "anotherschwab",
    "status": "exists",
    "profile_url": "https://x.com/anotherschwab",
    "checked_at": "2025-08-21T13:39:48.191300",
    "last_updated": "2025-08-21T13:39:48.191317"
  },
  "inahreads": {
    "original_username": "inahreads",
    "status": "exists",
    "profile_url": "https://x.com/inahreads",
    "checked_at": "2025-08-21T13:39:48.969593",
    "last_updated": "2025-08-21T13:39:48.969614"
  },
  "SilverFaeryhawk": {
    "original_username": "SilverFaeryhawk",
    "status": "exists",
    "profile_url": "https://x.com/SilverFaeryhawk",
    "checked_at": "2025-08-21T13:39:55.143761",
    "last_updated": "2025-08-21T13:39:55.144588"
  },
  "DanielXplode": {
    "original_username": "DanielXplode",
    "status": "exists",
    "profile_url": "https://x.com/DanielXplode",
    "checked_at": "2025-08-21T13:39:58.991385",
    "last_updated": "2025-08-21T13:39:58.991415"
  },
  "theveganwitch13": {
    "original_username": "theveganwitch13",
    "status": "exists",
    "profile_url": "https://x.com/theveganwitch13",
    "checked_at": "2025-08-21T13:40:00.101785",
    "last_updated": "2025-08-21T13:40:00.101802"
  },
  "bellatrix134340": {
    "original_username": "bellatrix134340",
    "status": "exists",
    "profile_url": "https://x.com/bellatrix134340",
    "checked_at": "2025-08-21T13:40:07.076586",
    "last_updated": "2025-08-21T13:40:07.076609"
  },
  "Pooks82Official": {
    "original_username": "Pooks82Official",
    "status": "exists",
    "profile_url": "https://x.com/Pooks82Official",
    "checked_at": "2025-08-21T13:40:09.692689",
    "last_updated": "2025-08-21T13:40:09.692698"
  },
  "ElizabethJhnson": {
    "original_username": "ElizabethJhnson",
    "status": "exists",
    "profile_url": "https://x.com/ElizabethJhnson",
    "checked_at": "2025-08-21T13:40:11.050425",
    "last_updated": "2025-08-21T13:40:11.050432"
  },
  "ScruffyBunnyNL": {
    "original_username": "ScruffyBunnyNL",
    "status": "exists",
    "profile_url": "https://x.com/ScruffyBunnyNL",
    "checked_at": "2025-08-21T13:40:17.869658",
    "last_updated": "2025-08-21T13:40:17.869693"
  },
  "kelly_renee1": {
    "original_username": "kelly_renee1",
    "status": "exists",
    "profile_url": "https://x.com/kelly_renee1",
    "checked_at": "2025-08-21T13:40:21.381106",
    "last_updated": "2025-08-21T13:40:21.381127"
  },
  "AnnaDreams_Art": {
    "original_username": "AnnaDreams_Art",
    "status": "exists",
    "profile_url": "https://x.com/AnnaDreams_Art",
    "checked_at": "2025-08-21T13:40:21.636132",
    "last_updated": "2025-08-21T13:40:21.636140"
  },
  "thebrittneyw": {
    "original_username": "thebrittneyw",
    "status": "exists",
    "profile_url": "https://x.com/thebrittneyw",
    "checked_at": "2025-08-21T13:40:29.640531",
    "last_updated": "2025-08-21T13:40:29.640552"
  },
  "stickpoet": {
    "original_username": "stickpoet",
    "status": "exists",
    "profile_url": "https://x.com/stickpoet",
    "checked_at": "2025-08-21T13:40:31.681629",
    "last_updated": "2025-08-21T13:40:31.681637"
  },
  "dwmdn": {
    "original_username": "dwmdn",
    "status": "exists",
    "profile_url": "https://x.com/dwmdn",
    "checked_at": "2025-08-21T13:40:32.071004",
    "last_updated": "2025-08-21T13:40:32.071013"
  },
  "mellodie_bh31": {
    "original_username": "mellodie_bh31",
    "status": "exists",
    "profile_url": "https://x.com/mellodie_bh31",
    "checked_at": "2025-08-21T13:40:40.722683",
    "last_updated": "2025-08-21T13:40:40.722693"
  },
  "kimluvmy": {
    "original_username": "kimluvmy",
    "status": "exists",
    "profile_url": "https://x.com/kimluvmy",
    "checked_at": "2025-08-21T13:40:42.051700",
    "last_updated": "2025-08-21T13:40:42.051712"
  },
  "kosherjellyfish": {
    "original_username": "kosherjellyfish",
    "status": "exists",
    "profile_url": "https://x.com/kosherjellyfish",
    "checked_at": "2025-08-21T13:40:42.311666",
    "last_updated": "2025-08-21T13:40:42.311675"
  },
  "aryllins": {
    "original_username": "aryllins",
    "status": "exists",
    "profile_url": "https://x.com/aryllins",
    "checked_at": "2025-08-21T13:40:51.556069",
    "last_updated": "2025-08-21T13:40:51.556115"
  },
  "LauraKatharineX": {
    "original_username": "LauraKatharineX",
    "status": "exists",
    "profile_url": "https://x.com/LauraKatharineX",
    "checked_at": "2025-08-21T13:40:53.790292",
    "last_updated": "2025-08-21T13:40:53.790302"
  },
  "clashville": {
    "original_username": "clashville",
    "status": "exists",
    "profile_url": "https://x.com/clashville",
    "checked_at": "2025-08-21T13:40:54.581886",
    "last_updated": "2025-08-21T13:40:54.581900"
  },
  "wapolzOfficial": {
    "original_username": "wapolzOfficial",
    "status": "exists",
    "profile_url": "https://x.com/wapolzOfficial",
    "checked_at": "2025-08-21T13:41:02.498872",
    "last_updated": "2025-08-21T13:41:02.498885"
  },
  "itslindyc": {
    "original_username": "itslindyc",
    "status": "exists",
    "profile_url": "https://x.com/itslindyc",
    "checked_at": "2025-08-21T13:41:04.939515",
    "last_updated": "2025-08-21T13:41:04.939527"
  },
  "AlyonaSchatzman": {
    "original_username": "AlyonaSchatzman",
    "status": "exists",
    "profile_url": "https://x.com/AlyonaSchatzman",
    "checked_at": "2025-08-21T13:41:06.168479",
    "last_updated": "2025-08-21T13:41:06.168489"
  },
  "thoughtinkling2": {
    "original_username": "thoughtinkling2",
    "status": "exists",
    "profile_url": "https://x.com/thoughtinkling2",
    "checked_at": "2025-08-21T13:41:13.045816",
    "last_updated": "2025-08-21T13:41:13.045842"
  },
  "Himmapaan": {
    "original_username": "Himmapaan",
    "status": "exists",
    "profile_url": "https://x.com/Himmapaan",
    "checked_at": "2025-08-21T13:41:16.354330",
    "last_updated": "2025-08-21T13:41:16.354357"
  },
  "titilayoxxiii": {
    "original_username": "titilayoxxiii",
    "status": "exists",
    "profile_url": "https://x.com/titilayoxxiii",
    "checked_at": "2025-08-21T13:41:17.236247",
    "last_updated": "2025-08-21T13:41:17.236262"
  },
  "CatelinCeleste": {
    "original_username": "CatelinCeleste",
    "status": "exists",
    "profile_url": "https://x.com/CatelinCeleste",
    "checked_at": "2025-08-21T13:41:25.203145",
    "last_updated": "2025-08-21T13:41:25.203162"
  },
  "Roxushi": {
    "original_username": "Roxushi",
    "status": "exists",
    "profile_url": "https://x.com/Roxushi",
    "checked_at": "2025-08-21T13:41:28.297415",
    "last_updated": "2025-08-21T13:41:28.297432"
  },
  "Uhmanduh": {
    "original_username": "Uhmanduh",
    "status": "exists",
    "profile_url": "https://x.com/Uhmanduh",
    "checked_at": "2025-08-21T13:41:28.320869",
    "last_updated": "2025-08-21T13:41:28.320884"
  },
  "willmadrazo": {
    "original_username": "willmadrazo",
    "status": "exists",
    "profile_url": "https://x.com/willmadrazo",
    "checked_at": "2025-08-21T13:41:37.296151",
    "last_updated": "2025-08-21T13:41:37.296166"
  },
  "AmizingSailorAJ": {
    "original_username": "AmizingSailorAJ",
    "status": "exists",
    "profile_url": "https://x.com/AmizingSailorAJ",
    "checked_at": "2025-08-21T13:41:40.488209",
    "last_updated": "2025-08-21T13:41:40.488226"
  },
  "subha26": {
    "original_username": "subha26",
    "status": "exists",
    "profile_url": "https://x.com/subha26",
    "checked_at": "2025-08-21T13:41:40.511149",
    "last_updated": "2025-08-21T13:41:40.511158"
  },
  "hahahafsa": {
    "original_username": "hahahafsa",
    "status": "exists",
    "profile_url": "https://x.com/hahahafsa",
    "checked_at": "2025-08-21T13:41:47.695565",
    "last_updated": "2025-08-21T13:41:47.695597"
  },
  "ohh_livi_yuhh": {
    "original_username": "ohh_livi_yuhh",
    "status": "exists",
    "profile_url": "https://x.com/ohh_livi_yuhh",
    "checked_at": "2025-08-21T13:41:51.391052",
    "last_updated": "2025-08-21T13:41:51.391083"
  },
  "joshhrayy": {
    "original_username": "joshhrayy",
    "status": "exists",
    "profile_url": "https://x.com/joshhrayy",
    "checked_at": "2025-08-21T13:41:52.431176",
    "last_updated": "2025-08-21T13:41:52.431189"
  },
  "ImChillLikeThat": {
    "original_username": "ImChillLikeThat",
    "status": "exists",
    "profile_url": "https://x.com/ImChillLikeThat",
    "checked_at": "2025-08-21T13:41:58.632980",
    "last_updated": "2025-08-21T13:41:58.633023"
  },
  "Hussain_gg": {
    "original_username": "Hussain_gg",
    "status": "exists",
    "profile_url": "https://x.com/Hussain_gg",
    "checked_at": "2025-08-21T13:42:02.500372",
    "last_updated": "2025-08-21T13:42:02.500391"
  },
  "delia_a": {
    "original_username": "delia_a",
    "status": "exists",
    "profile_url": "https://x.com/delia_a",
    "checked_at": "2025-08-21T13:42:03.055085",
    "last_updated": "2025-08-21T13:42:03.055100"
  },
  "blovesastro": {
    "original_username": "blovesastro",
    "status": "exists",
    "profile_url": "https://x.com/blovesastro",
    "checked_at": "2025-08-21T13:42:09.772735",
    "last_updated": "2025-08-21T13:42:09.772770"
  },
  "_niaow": {
    "original_username": "_niaow",
    "status": "exists",
    "profile_url": "https://x.com/_niaow",
    "checked_at": "2025-08-21T13:42:13.235864",
    "last_updated": "2025-08-21T13:42:13.235899"
  },
  "brucethegirl": {
    "original_username": "brucethegirl",
    "status": "exists",
    "profile_url": "https://x.com/brucethegirl",
    "checked_at": "2025-08-21T13:42:14.587095",
    "last_updated": "2025-08-21T13:42:14.587105"
  },
  "MirenxOTM": {
    "original_username": "MirenxOTM",
    "status": "exists",
    "profile_url": "https://x.com/MirenxOTM",
    "checked_at": "2025-08-21T13:42:21.332955",
    "last_updated": "2025-08-21T13:42:21.332991"
  },
  "BiancaLoran": {
    "original_username": "BiancaLoran",
    "status": "exists",
    "profile_url": "https://x.com/BiancaLoran",
    "checked_at": "2025-08-21T13:42:23.881285",
    "last_updated": "2025-08-21T13:42:23.881305"
  },
  "jiminstreble": {
    "original_username": "jiminstreble",
    "status": "exists",
    "profile_url": "https://x.com/jiminstreble",
    "checked_at": "2025-08-21T13:42:24.917105",
    "last_updated": "2025-08-21T13:42:24.917121"
  },
  "MahleSoul": {
    "original_username": "MahleSoul",
    "status": "exists",
    "profile_url": "https://x.com/MahleSoul",
    "checked_at": "2025-08-21T13:42:31.717981",
    "last_updated": "2025-08-21T13:42:31.718013"
  },
  "wicked_jr89": {
    "original_username": "wicked_jr89",
    "status": "exists",
    "profile_url": "https://x.com/wicked_jr89",
    "checked_at": "2025-08-21T13:42:34.481818",
    "last_updated": "2025-08-21T13:42:34.481849"
  },
  "bexcapades": {
    "original_username": "bexcapades",
    "status": "exists",
    "profile_url": "https://x.com/bexcapades",
    "checked_at": "2025-08-21T13:42:36.741418",
    "last_updated": "2025-08-21T13:42:36.741429"
  },
  "sbsestra": {
    "original_username": "sbsestra",
    "status": "exists",
    "profile_url": "https://x.com/sbsestra",
    "checked_at": "2025-08-21T13:42:42.156326",
    "last_updated": "2025-08-21T13:42:42.156354"
  },
  "thankyou2NE1": {
    "original_username": "thankyou2NE1",
    "status": "exists",
    "profile_url": "https://x.com/thankyou2NE1",
    "checked_at": "2025-08-21T13:42:46.400647",
    "last_updated": "2025-08-21T13:42:46.400684"
  },
  "tangledtori": {
    "original_username": "tangledtori",
    "status": "exists",
    "profile_url": "https://x.com/tangledtori",
    "checked_at": "2025-08-21T13:42:47.567284",
    "last_updated": "2025-08-21T13:42:47.567293"
  },
  "ArmoniaLise": {
    "original_username": "ArmoniaLise",
    "status": "exists",
    "profile_url": "https://x.com/ArmoniaLise",
    "checked_at": "2025-08-21T13:42:53.606828",
    "last_updated": "2025-08-21T13:42:53.606874"
  },
  "yoongsvibe": {
    "original_username": "yoongsvibe",
    "status": "exists",
    "profile_url": "https://x.com/yoongsvibe",
    "checked_at": "2025-08-21T13:42:57.620318",
    "last_updated": "2025-08-21T13:42:57.620355"
  },
  "Purrsnikitty07": {
    "original_username": "Purrsnikitty07",
    "status": "exists",
    "profile_url": "https://x.com/Purrsnikitty07",
    "checked_at": "2025-08-21T13:42:58.410915",
    "last_updated": "2025-08-21T13:42:58.410943"
  },
  "CalmJTM": {
    "original_username": "CalmJTM",
    "status": "exists",
    "profile_url": "https://x.com/CalmJTM",
    "checked_at": "2025-08-21T13:43:04.952639",
    "last_updated": "2025-08-21T13:43:04.952667"
  },
  "thearlynist": {
    "original_username": "thearlynist",
    "status": "exists",
    "profile_url": "https://x.com/thearlynist",
    "checked_at": "2025-08-21T13:43:09.138377",
    "last_updated": "2025-08-21T13:43:09.138415"
  },
  "danibrstl": {
    "original_username": "danibrstl",
    "status": "exists",
    "profile_url": "https://x.com/danibrstl",
    "checked_at": "2025-08-21T13:43:10.432047",
    "last_updated": "2025-08-21T13:43:10.432055"
  },
  "FabuPonah": {
    "original_username": "FabuPonah",
    "status": "exists",
    "profile_url": "https://x.com/FabuPonah",
    "checked_at": "2025-08-21T13:43:16.942323",
    "last_updated": "2025-08-21T13:43:16.942365"
  },
  "luisah92": {
    "original_username": "luisah92",
    "status": "exists",
    "profile_url": "https://x.com/luisah92",
    "checked_at": "2025-08-21T13:43:19.399538",
    "last_updated": "2025-08-21T13:43:19.399551"
  },
  "shaunaparmesan": {
    "original_username": "shaunaparmesan",
    "status": "exists",
    "profile_url": "https://x.com/shaunaparmesan",
    "checked_at": "2025-08-21T13:43:21.068358",
    "last_updated": "2025-08-21T13:43:21.068366"
  },
  "shelbylcole": {
    "original_username": "shelbylcole",
    "status": "exists",
    "profile_url": "https://x.com/shelbylcole",
    "checked_at": "2025-08-21T13:43:29.106122",
    "last_updated": "2025-08-21T13:43:29.106151"
  },
  "MattSloanWrites": {
    "original_username": "MattSloanWrites",
    "status": "exists",
    "profile_url": "https://x.com/MattSloanWrites",
    "checked_at": "2025-08-21T13:43:30.041120",
    "last_updated": "2025-08-21T13:43:30.041136"
  },
  "pinkygirl06": {
    "original_username": "pinkygirl06",
    "status": "exists",
    "profile_url": "https://x.com/pinkygirl06",
    "checked_at": "2025-08-21T13:43:32.031816",
    "last_updated": "2025-08-21T13:43:32.031822"
  },
  "octoberxswimmer": {
    "original_username": "octoberxswimmer",
    "status": "exists",
    "profile_url": "https://x.com/octoberxswimmer",
    "checked_at": "2025-08-21T13:43:39.867645",
    "last_updated": "2025-08-21T13:43:39.867661"
  },
  "amdmw": {
    "original_username": "amdmw",
    "status": "exists",
    "profile_url": "https://x.com/amdmw",
    "checked_at": "2025-08-21T13:43:42.273842",
    "last_updated": "2025-08-21T13:43:42.273872"
  },
  "MatthewBoulden": {
    "original_username": "MatthewBoulden",
    "status": "exists",
    "profile_url": "https://x.com/MatthewBoulden",
    "checked_at": "2025-08-21T13:43:42.871964",
    "last_updated": "2025-08-21T13:43:42.872013"
  }
}